libname/__init__.py
libname/raytux.py
RayTux-0.0.1.dist-info/METADATA
RayTux-0.0.1.dist-info/WHEEL
RayTux-0.0.1.dist-info/top_level.txt
RayTux-0.0.1.dist-info/RECORD
