Metadata-Version: 2.1
Name: RayTux
Version: 0.0.1
Summary: great tool to help you with your programming journy
Author: Seartuxe (Ali Hadwan)
Author-email: raytux.py@gmail.com
Keywords: python,password,keyboard_input
Classifier: Development Status :: 1 - Planning
Classifier: Intended Audience :: Developers
Classifier: Programming Language :: Python :: 3
Classifier: Operating System :: Unix
Classifier: Operating System :: MacOS :: MacOS X
Classifier: Operating System :: Microsoft :: Windows
Requires-Dist: keyboard
